camel_terminal_toolkit/__init__.py
camel_terminal_toolkit/server.py
terminal_toolkit_mcp-0.1.2.dist-info/METADATA
terminal_toolkit_mcp-0.1.2.dist-info/WHEEL
terminal_toolkit_mcp-0.1.2.dist-info/entry_points.txt
terminal_toolkit_mcp-0.1.2.dist-info/top_level.txt
terminal_toolkit_mcp-0.1.2.dist-info/RECORD
