Metadata-Version: 2.4
Name: terminal-toolkit-mcp
Version: 0.1.2
Summary: CAMEL Terminal Toolkit as a standalone MCP server
Author-email: "CAMEL-AI.org" <noreply@camel-ai.org>
License-Expression: Apache-2.0
Project-URL: Homepage, https://github.com/camel-ai/terminal-toolkit-mcp
Project-URL: Repository, https://github.com/camel-ai/terminal-toolkit-mcp
Project-URL: Documentation, https://docs.camel-ai.org
Project-URL: Bug Tracker, https://github.com/camel-ai/terminal-toolkit-mcp/issues
Keywords: mcp,terminal,shell,camel,ai,toolkit,server
Classifier: Development Status :: 4 - Beta
Classifier: Intended Audience :: Developers
Classifier: Operating System :: OS Independent
Classifier: Programming Language :: Python :: 3
Classifier: Programming Language :: Python :: 3.10
Classifier: Programming Language :: Python :: 3.11
Classifier: Programming Language :: Python :: 3.12
Classifier: Topic :: Software Development :: Libraries :: Python Modules
Classifier: Topic :: System :: Shells
Classifier: Topic :: Scientific/Engineering :: Artificial Intelligence
Requires-Python: >=3.10
Requires-Dist: mcp>=1.0.0
Requires-Dist: pydantic>=2.0.0
Requires-Dist: typing-extensions>=4.0.0
Requires-Dist: camel-ai>=0.2.74
Provides-Extra: dev
Requires-Dist: pytest>=7.0.0; extra == "dev"
Requires-Dist: pytest-asyncio>=0.21.0; extra == "dev"
Requires-Dist: black>=23.0.0; extra == "dev"
Requires-Dist: ruff>=0.1.0; extra == "dev"
Requires-Dist: mypy>=1.0.0; extra == "dev"
Requires-Dist: build>=1.0.0; extra == "dev"
Requires-Dist: twine>=5.0.0; extra == "dev"
